pytz_convert/__init__.py
pytz_convert/timezone_utils.py
pytz_convert-0.2.9.dist-info/DESCRIPTION.rst
pytz_convert-0.2.9.dist-info/METADATA
pytz_convert-0.2.9.dist-info/RECORD
pytz_convert-0.2.9.dist-info/WHEEL
pytz_convert-0.2.9.dist-info/metadata.json
pytz_convert-0.2.9.dist-info/top_level.txt
