Metadata-Version: 2.0
Name: pytz-convert
Version: 0.2.9
Summary: Extension of Python package pytz providing functions for converting timezone names, abbreviations, and offsets.
Home-page: https://github.com/tuneinc/pycountry-convert
Author: TUNE Inc.
Author-email: jefft@tune.com
License: MIT License
Download-URL: https://github.com/TuneLab/pytz-convert/archive/v0.2.9.tar.gz
Keywords: pytz convert tune
Platform: UNKNOWN
Classifier: Development Status :: 5 - Production/Stable
Classifier: Intended Audience :: Developers
Classifier: Operating System :: OS Independent
Classifier: Natural Language :: English
Classifier: License :: OSI Approved :: MIT License
Classifier: Programming Language :: Python
Classifier: Programming Language :: Python :: 2.7
Classifier: Programming Language :: Python :: 3
Classifier: Programming Language :: Python :: 3.1
Classifier: Programming Language :: Python :: 3.2
Classifier: Programming Language :: Python :: 3.3
Classifier: Programming Language :: Python :: 3.4
Classifier: Programming Language :: Python :: 3.5
Classifier: Programming Language :: Python :: 3.6
Classifier: Programming Language :: Python :: Implementation :: PyPy
Requires-Dist: pprintpp (>=0.3.0)
Requires-Dist: python-dateutil (>=2.6.1)
Requires-Dist: pytest (>=3.2.5)
Requires-Dist: pytest-mock (>=1.6.3)
Requires-Dist: pytest-cov (>=2.5.1)
Requires-Dist: pytz (>=2017.3)
Requires-Dist: wheel (>=0.30.0)
